team_formation/__init__.py
team_formation/__main__.py
team_formation/_version.txt
team_formation/team_assignment.py
team_formation/team_assignment_ui.py
team_formation/working_time.py
team_formation/api/README.md
team_formation/api/__init__.py
team_formation/api/callbacks.py
team_formation/api/main.py
team_formation/api/models.py
team_formation-1.6.1.dist-info/METADATA
team_formation-1.6.1.dist-info/WHEEL
team_formation-1.6.1.dist-info/entry_points.txt
team_formation-1.6.1.dist-info/licenses/LICENSE
team_formation-1.6.1.dist-info/RECORD
