Metadata-Version: 2.4
Name: team-formation
Version: 1.6.1
Summary: A tool to form teams from a larger group based on weighted constraints
Project-URL: Homepage, https://github.com/harvard-hbs/team-formation/
Project-URL: Changelog, https://raw.githubusercontent.com/harvard-hbs/team-formation/refs/heads/main/CHANGELOG.md
Author-email: Brent Benson <bbenson@hbs.edu>
License: MIT License
License-File: LICENSE
Keywords: clustering,diversity,team,team formation
Classifier: License :: OSI Approved :: MIT License
Classifier: Programming Language :: Python
Classifier: Programming Language :: Python :: 3
Requires-Python: >=3.8
Requires-Dist: fastapi>=0.104.0
Requires-Dist: ortools>=9.2
Requires-Dist: pandas>=2.0
Requires-Dist: sse-starlette>=1.6.5
Requires-Dist: streamlit>=1.30
Requires-Dist: uvicorn[standard]>=0.24.0
Requires-Dist: watchdog>=4.0.2
Provides-Extra: dev
Requires-Dist: build; extra == 'dev'
Requires-Dist: hatchling; extra == 'dev'
Requires-Dist: httpx; extra == 'dev'
Requires-Dist: pytest; extra == 'dev'
Requires-Dist: pytest-asyncio; extra == 'dev'
Requires-Dist: twine; extra == 'dev'
